01_combinational_logic/01_04_mux_index/01_04_mux_index.sv
//----------------------------------------------------------------------------
// Example
//----------------------------------------------------------------------------

module mux_2_1
(
  input  [3:0] d0, d1,
  input        sel,
  output [3:0] y
);

  logic [3:0] d [0:1];

  assign d [0] = d0;
  assign d [1] = d1;

  assign y = d [sel];

endmodule

//----------------------------------------------------------------------------
// Task
//----------------------------------------------------------------------------

module mux_4_1
(
  input  [3:0] d0, d1, d2, d3,
  input  [1:0] sel,
  output [3:0] y
);

  // Task:
  // Using code for mux_2_1 as an example,
  // write code for 4:1 mux using array index

  logic [3:0] d [0:3];

  // logic == type 
  // [3:0] == количество бит (0000, 0001, ...), которое может принимать каждый из d0, d1, d2, d3 проводов
  // d == имя 
  // [0:3] == массив из проводов выше (4 штуки)

  assign d [0] = d0;
  assign d [1] = d1;
  assign d [2] = d2;
  assign d [3] = d3;

  assign y = d [sel];

endmodule

01_combinational_logic/01_01_mux_question/testbench.sv
`include "util.svh"

module testbench;

  logic [3:0] d0, d1, d2, d3;
  logic [1:0] sel;
  logic [3:0] y;

  mux_4_1 inst
  (
    .d0  (d0), .d1 (d1), .d2 (d2), .d3 (d3),
    .sel (sel),
    .y   (y)
  );

  task test
    (
      input [3:0] td0, td1, td2, td3,
      input [1:0] tsel,
      input [3:0] ty
    );

    { d0, d1, d2, d3, sel } = { td0, td1, td2, td3, tsel };

    # 1;

    if (y !== ty)
      begin
        $display("FAIL %s", `__FILE__);
        $display("++ INPUT    => {%s, %s, %s, %s, %s}", `PH(d0), `PH(d1), `PH(d2), `PH(d3), `PH(sel));
        $display("++ EXPECTED => {%s}", `PH(ty));
        $display("++ ACTUAL   => {%s}", `PH(y));
        $finish(1);
      end

  endtask

  initial
    begin
   $dumpfile("out.vcd");
   $dumpvars(0, testbench);
      test ('ha, 'hb, 'hc, 'hd, 0, 'ha);
      test ('ha, 'hb, 'hc, 'hd, 1, 'hb);
      test ('ha, 'hb, 'hc, 'hd, 2, 'hc);
      test ('ha, 'hb, 'hc, 'hd, 3, 'hd);

      test (7, 10, 3, 'x, 0, 7);
      test (7, 10, 3, 'x, 1, 10);
      test (7, 10, 3, 'x, 2, 3);
      test (7, 10, 3, 'x, 3, 'x);

      $display ("PASS %s", `__FILE__);
      $finish;
    end

endmodule

01_combinational_logic/out.vcd
$date
	Mon Mar 31 20:55:56 2025
$end
$version
	Icarus Verilog
$end
$timescale
	1s
$end
$scope module testbench $end
$var wire 4 ! y [3:0] $end
$var reg 4 " d0 [3:0] $end
$var reg 4 # d1 [3:0] $end
$var reg 4 $ d2 [3:0] $end
$var reg 4 % d3 [3:0] $end
$var reg 2 & sel [1:0] $end
$scope module inst $end
$var wire 4 ' d0 [3:0] $end
$var wire 4 ( d1 [3:0] $end
$var wire 4 ) d2 [3:0] $end
$var wire 4 * d3 [3:0] $end
$var wire 2 + sel [1:0] $end
$var wire 4 , y [3:0] $end
$upscope $end
$scope task test $end
$var reg 4 - td0 [3:0] $end
$var reg 4 . td1 [3:0] $end
$var reg 4 / td2 [3:0] $end
$var reg 4 0 td3 [3:0] $end
$var reg 2 1 tsel [1:0] $end
$var reg 4 2 ty [3:0] $end
$upscope $end
$upscope $end
$enddefinitions $end
$comment Show the parameter values. $end
$dumpall
$end
#0
$dumpvars
b1010 2
b0 1
b1101 0
b1100 /
b1011 .
b1010 -
b1010 ,
b0 +
b1101 *
b1100 )
b1011 (
b1010 '
b0 &
b1101 %
b1100 $
b1011 #
b1010 "
b1010 !
$end
#1
b1011 !
b1011 ,
b1 &
b1 +
b1011 2
b1 1
#2
b1100 !
b1100 ,
b10 &
b10 +
b1100 2
b10 1
#3
b1101 !
b1101 ,
b11 &
b11 +
b1101 2
b11 1
#4
b111 !
b111 ,
b111 "
b111 '
b1010 #
b1010 (
b11 $
b11 )
bx %
bx *
b0 &
b0 +
b111 2
b0 1
bx 0
b11 /
b1010 .
b111 -
#5
b1010 !
b1010 ,
b1 &
b1 +
b1010 2
b1 1
#6
b11 !
b11 ,
b10 &
b10 +
b11 2
b10 1
#7
bx !
bx ,
b11 &
b11 +
bx 2
b11 1
