04_arithmetics_and_pipelining/04_04_four_ways_of_doing_shift/04_04_four_ways_of_doing_shift.sv
//----------------------------------------------------------------------------
// Example
//----------------------------------------------------------------------------

module left_shift_of_8_by_3_using_left_shift_operation (input  [7:0] a, output [7:0] res);

  assign res = a << 3;

endmodule

// We are ignoring bits a[7:5] on purpose
// verilator lint_off UNUSEDSIGNAL

module left_shift_of_8_by_3_using_concatenation (input  [7:0] a, output [7:0] res);

  assign res = { a [4:0], 3'b0 };

endmodule

// verilator lint_on UNUSEDSIGNAL

module left_shift_of_8_by_3_using_for_inside_always (input  [7:0] a, output logic [7:0] res);

  always_comb
    for (int i = 0; i < 8; i ++)
      res [i] = i < 3 ? 1'b0 : a [i - 3];

endmodule

// We are ignoring bits a[7:5] on purpose
// verilator lint_off UNUSEDSIGNAL

module left_shift_of_8_by_3_using_for_inside_generate (input  [7:0] a, output [7:0] res);

  genvar i;

  generate
    for (i = 0; i < 8; i ++)
      if (i < 3) begin : zero_bit_gen
        assign res [i] = 1'b0;
      end
      else begin : shifted_bit_gen
        assign res [i] = a [i - 3];
      end
  endgenerate

endmodule

// verilator lint_on UNUSEDSIGNAL

//----------------------------------------------------------------------------
// Task
//----------------------------------------------------------------------------

module right_shift_of_N_by_S_using_right_shift_operation
# (parameter N = 8, S = 3)
(input  [N - 1:0] a, output [N - 1:0] res);

  // Task:
  //
  // Implement a parameterized module
  // that shifts the unsigned input by S bits to the right
  // using logical right shift operation

  assign res = a >> S;

endmodule

// We are ignoring some bits on purpose
// verilator lint_off UNUSEDSIGNAL

module right_shift_of_N_by_S_using_concatenation
# (parameter N = 8, S = 3)
(input  [N - 1:0] a, output [N - 1:0] res);

  // Task:
  //
  // Implement a parameterized module
  // that shifts the unsigned input by S bits to the right
  // using concatenation operation

  assign res = {{S{1'b0}}, a[(N-1):S]};

endmodule

// verilator lint_on UNUSEDSIGNAL

module right_shift_of_N_by_S_using_for_inside_always
# (parameter N = 8, S = 3)
(input  [N - 1:0] a, output logic [N - 1:0] res);

  // Task:
  //
  // Implement a parameterized module
  // that shifts the unsigned input by S bits to the right
  // using "for" inside "always_comb"

  always_comb 
  begin
    for (int i = 0; i < N; ++i)
      res[i] = (i >= N - S) ? 1'b0 : a[i + S];
  end

endmodule

module right_shift_of_N_by_S_using_for_inside_generate
# (parameter N = 8, S = 3)
(input  [N - 1:0] a, output [N - 1:0] res);

  // Task:
  //
  // Implement a parameterized module
  // that shifts the unsigned input by S bits to the right
  // sing "generate" and "for"

  genvar i;

  generate
    for (i = 0; i < N; ++i)
      if (i > N - S - 1)
        assign res [i] = 1'b0;
      else
        assign res [i] = a[i + S];
  endgenerate

endmodule

04_arithmetics_and_pipelining/04_04_four_ways_of_doing_shift/testbench.sv
module testbench;

  localparam N = 8, S = 3;

  logic [N - 1:0] a, res [0:7];

  left_shift_of_8_by_3_using_left_shift_operation  i0 (a, res [0]);
  left_shift_of_8_by_3_using_concatenation         i1 (a, res [1]);
  left_shift_of_8_by_3_using_for_inside_always     i2 (a, res [2]);
  left_shift_of_8_by_3_using_for_inside_generate   i3 (a, res [3]);

  right_shift_of_N_by_S_using_right_shift_operation
  # (.N (N), .S (S)) i4 (a, res [4]);

  right_shift_of_N_by_S_using_concatenation
  # (.N (N), .S (S)) i5 (a, res [5]);

  right_shift_of_N_by_S_using_for_inside_always
  # (.N (N), .S (S)) i6 (a, res [6]);

  right_shift_of_N_by_S_using_for_inside_generate
  # (.N (N), .S (S)) i7 (a, res [7]);

  initial
  begin
    $dumpfile("out.vcd");
    $dumpvars(0, testbench);
    repeat (20)
    begin
      a = N' ($urandom());
      # 1

      $write ("TEST %b", a);

      for (int i = 0; i < 8; i ++)
        $write (" %b", res [i]);

      $display;

      for (int i = 0; i < 8; i ++)
        if (res [i] !== res [i / 4 * 4])
        begin
          $display ("FAIL %s - see above", `__FILE__);
          $finish;
        end
    end

    $display ("PASS %s", `__FILE__);
    $finish;
  end

endmodule

04_arithmetics_and_pipelining/out.vcd
$date
	Wed Apr 23 21:57:31 2025
$end
$version
	Icarus Verilog
$end
$timescale
	1s
$end
$scope module testbench $end
$var parameter 32 ! N $end
$var parameter 32 " S $end
$var reg 8 # a [7:0] $end
$scope module i0 $end
$var wire 8 $ a [7:0] $end
$var wire 8 % res [7:0] $end
$upscope $end
$scope module i1 $end
$var wire 8 & a [7:0] $end
$var wire 8 ' res [7:0] $end
$upscope $end
$scope module i2 $end
$var wire 8 ( a [7:0] $end
$var reg 8 ) res [7:0] $end
$scope begin $ivl_for_loop0 $end
$var integer 32 * i [31:0] $end
$upscope $end
$upscope $end
$scope module i3 $end
$var wire 8 + a [7:0] $end
$var wire 8 , res [7:0] $end
$scope begin genblk1[0] $end
$var parameter 2 - i $end
$scope begin zero_bit_gen $end
$upscope $end
$upscope $end
$scope begin genblk1[1] $end
$var parameter 2 . i $end
$scope begin zero_bit_gen $end
$upscope $end
$upscope $end
$scope begin genblk1[2] $end
$var parameter 3 / i $end
$scope begin zero_bit_gen $end
$upscope $end
$upscope $end
$scope begin genblk1[3] $end
$var parameter 3 0 i $end
$scope begin shifted_bit_gen $end
$upscope $end
$upscope $end
$scope begin genblk1[4] $end
$var parameter 4 1 i $end
$scope begin shifted_bit_gen $end
$upscope $end
$upscope $end
$scope begin genblk1[5] $end
$var parameter 4 2 i $end
$scope begin shifted_bit_gen $end
$upscope $end
$upscope $end
$scope begin genblk1[6] $end
$var parameter 4 3 i $end
$scope begin shifted_bit_gen $end
$upscope $end
$upscope $end
$scope begin genblk1[7] $end
$var parameter 4 4 i $end
$scope begin shifted_bit_gen $end
$upscope $end
$upscope $end
$upscope $end
$scope module i4 $end
$var wire 8 5 a [7:0] $end
$var wire 8 6 res [7:0] $end
$var parameter 32 7 N $end
$var parameter 32 8 S $end
$upscope $end
$scope module i5 $end
$var wire 8 9 a [7:0] $end
$var wire 8 : res [7:0] $end
$var parameter 32 ; N $end
$var parameter 32 < S $end
$upscope $end
$scope module i6 $end
$var wire 8 = a [7:0] $end
$var parameter 32 > N $end
$var parameter 32 ? S $end
$var reg 8 @ res [7:0] $end
$scope begin $ivl_for_loop1 $end
$var integer 32 A i [31:0] $end
$upscope $end
$upscope $end
$scope module i7 $end
$var wire 8 B a [7:0] $end
$var wire 8 C res [7:0] $end
$var parameter 32 D N $end
$var parameter 32 E S $end
$scope begin genblk1[0] $end
$var parameter 2 F i $end
$scope begin genblk1 $end
$upscope $end
$upscope $end
$scope begin genblk1[1] $end
$var parameter 2 G i $end
$scope begin genblk1 $end
$upscope $end
$upscope $end
$scope begin genblk1[2] $end
$var parameter 3 H i $end
$scope begin genblk1 $end
$upscope $end
$upscope $end
$scope begin genblk1[3] $end
$var parameter 3 I i $end
$scope begin genblk1 $end
$upscope $end
$upscope $end
$scope begin genblk1[4] $end
$var parameter 4 J i $end
$scope begin genblk1 $end
$upscope $end
$upscope $end
$scope begin genblk1[5] $end
$var parameter 4 K i $end
$scope begin genblk1 $end
$upscope $end
$upscope $end
$scope begin genblk1[6] $end
$var parameter 4 L i $end
$scope begin genblk1 $end
$upscope $end
$upscope $end
$scope begin genblk1[7] $end
$var parameter 4 M i $end
$scope begin genblk1 $end
$upscope $end
$upscope $end
$upscope $end
$scope begin $ivl_for_loop2 $end
$var integer 32 N i [31:0] $end
$upscope $end
$scope begin $ivl_for_loop3 $end
$var integer 32 O i [31:0] $end
$upscope $end
$upscope $end
$enddefinitions $end
$comment Show the parameter values. $end
$dumpall
b111 M
b110 L
b101 K
b100 J
b11 I
b10 H
b1 G
b0 F
b11 E
b1000 D
b11 ?
b1000 >
b11 <
b1000 ;
b11 8
b1000 7
b111 4
b110 3
b101 2
b100 1
b11 0
b10 /
b1 .
b0 -
b11 "
b1000 !
$end
#0
$dumpvars
b0 O
b0 N
b100 C
b100100 B
b1000 A
b100 @
b100100 =
b100 :
b100100 9
b100 6
b100100 5
b100000 ,
b100100 +
b1000 *
b100000 )
b100100 (
b100000 '
b100100 &
b100000 %
b100100 $
b100100 #
$end
#1
b1000 %
b1000 '
b1000 )
b1000 *
b10000 @
b1000 A
b1000 ,
b10000 6
b10000 :
b10000 C
b10000001 #
b10000001 $
b10000001 &
b10000001 (
b10000001 +
b10000001 5
b10000001 9
b10000001 =
b10000001 B
b1000 O
b1000 N
#2
b1001000 %
b1001000 '
b1001000 )
b1000 *
b1 @
b1000 A
b1001000 ,
b1 6
b1 :
b1 C
b1001 #
b1001 $
b1001 &
b1001 (
b1001 +
b1001 5
b1001 9
b1001 =
b1001 B
b1000 O
b1000 N
#3
b11000 %
b11000 '
b11000 )
b1000 *
b1100 @
b1000 A
b11000 ,
b1100 6
b1100 :
b1100 C
b1100011 #
b1100011 $
b1100011 &
b1100011 (
b1100011 +
b1100011 5
b1100011 9
b1100011 =
b1100011 B
b1000 O
b1000 N
#4
b1101000 %
b1101000 '
b1101000 )
b1000 *
b1 @
b1000 A
b1101000 ,
b1 6
b1 :
b1 C
b1101 #
b1101 $
b1101 &
b1101 (
b1101 +
b1101 5
b1101 9
b1101 =
b1101 B
b1000 O
b1000 N
#5
b1000 *
b10001 @
b1000 A
b10001 6
b10001 :
b10001 C
b10001101 #
b10001101 $
b10001101 &
b10001101 (
b10001101 +
b10001101 5
b10001101 9
b10001101 =
b10001101 B
b1000 O
b1000 N
#6
b101000 %
b101000 '
b101000 )
b1000 *
b1100 @
b1000 A
b101000 ,
b1100 6
b1100 :
b1100 C
b1100101 #
b1100101 $
b1100101 &
b1100101 (
b1100101 +
b1100101 5
b1100101 9
b1100101 =
b1100101 B
b1000 O
b1000 N
#7
b10010000 %
b10010000 '
b10010000 )
b1000 *
b10 @
b1000 A
b10010000 ,
b10 6
b10 :
b10 C
b10010 #
b10010 $
b10010 &
b10010 (
b10010 +
b10010 5
b10010 9
b10010 =
b10010 B
b1000 O
b1000 N
#8
b1000 %
b1000 '
b1000 )
b1000 *
b0 @
b1000 A
b1000 ,
b0 6
b0 :
b0 C
b1 #
b1 $
b1 &
b1 (
b1 +
b1 5
b1 9
b1 =
b1 B
b1000 O
b1000 N
#9
b1101000 %
b1101000 '
b1101000 )
b1000 *
b1 @
b1000 A
b1101000 ,
b1 6
b1 :
b1 C
b1101 #
b1101 $
b1101 &
b1101 (
b1101 +
b1101 5
b1101 9
b1101 =
b1101 B
b1000 O
b1000 N
#10
b10110000 %
b10110000 '
b10110000 )
b1000 *
b1110 @
b1000 A
b10110000 ,
b1110 6
b1110 :
b1110 C
b1110110 #
b1110110 $
b1110110 &
b1110110 (
b1110110 +
b1110110 5
b1110110 9
b1110110 =
b1110110 B
b1000 O
b1000 N
#11
b11101000 %
b11101000 '
b11101000 )
b1000 *
b111 @
b1000 A
b11101000 ,
b111 6
b111 :
b111 C
b111101 #
b111101 $
b111101 &
b111101 (
b111101 +
b111101 5
b111101 9
b111101 =
b111101 B
b1000 O
b1000 N
#12
b1101000 %
b1101000 '
b1101000 )
b1000 *
b11101 @
b1000 A
b1101000 ,
b11101 6
b11101 :
b11101 C
b11101101 #
b11101101 $
b11101101 &
b11101101 (
b11101101 +
b11101101 5
b11101101 9
b11101101 =
b11101101 B
b1000 O
b1000 N
#13
b1100000 %
b1100000 '
b1100000 )
b1000 *
b10001 @
b1000 A
b1100000 ,
b10001 6
b10001 :
b10001 C
b10001100 #
b10001100 $
b10001100 &
b10001100 (
b10001100 +
b10001100 5
b10001100 9
b10001100 =
b10001100 B
b1000 O
b1000 N
#14
b11001000 %
b11001000 '
b11001000 )
b1000 *
b11111 @
b1000 A
b11001000 ,
b11111 6
b11111 :
b11111 C
b11111001 #
b11111001 $
b11111001 &
b11111001 (
b11111001 +
b11111001 5
b11111001 9
b11111001 =
b11111001 B
b1000 O
b1000 N
#15
b110000 %
b110000 '
b110000 )
b1000 *
b11000 @
b1000 A
b110000 ,
b11000 6
b11000 :
b11000 C
b11000110 #
b11000110 $
b11000110 &
b11000110 (
b11000110 +
b11000110 5
b11000110 9
b11000110 =
b11000110 B
b1000 O
b1000 N
#16
b101000 %
b101000 '
b101000 )
b1000 *
b1000 A
b101000 ,
b11000101 #
b11000101 $
b11000101 &
b11000101 (
b11000101 +
b11000101 5
b11000101 9
b11000101 =
b11000101 B
b1000 O
b1000 N
#17
b1010000 %
b1010000 '
b1010000 )
b1000 *
b10101 @
b1000 A
b1010000 ,
b10101 6
b10101 :
b10101 C
b10101010 #
b10101010 $
b10101010 &
b10101010 (
b10101010 +
b10101010 5
b10101010 9
b10101010 =
b10101010 B
b1000 O
b1000 N
#18
b101000 %
b101000 '
b101000 )
b1000 *
b11100 @
b1000 A
b101000 ,
b11100 6
b11100 :
b11100 C
b11100101 #
b11100101 $
b11100101 &
b11100101 (
b11100101 +
b11100101 5
b11100101 9
b11100101 =
b11100101 B
b1000 O
b1000 N
#19
b10111000 %
b10111000 '
b10111000 )
b1000 *
b1110 @
b1000 A
b10111000 ,
b1110 6
b1110 :
b1110 C
b1110111 #
b1110111 $
b1110111 &
b1110111 (
b1110111 +
b1110111 5
b1110111 9
b1110111 =
b1110111 B
b1000 O
b1000 N
#20
b1000 O
b1000 N
